caboodle/__init__.py
caboodle/artifacts.py
caboodle/artifacts_test.py
caboodle/coffer.py
caboodle/coffer_test.py
caboodle/gcs.py
the_whole_caboodle-0.2.17.dist-info/LICENSE
the_whole_caboodle-0.2.17.dist-info/WHEEL
the_whole_caboodle-0.2.17.dist-info/METADATA
the_whole_caboodle-0.2.17.dist-info/RECORD
