Metadata-Version: 2.1
Name: the-whole-caboodle
Version: 0.2.17
Summary: Utilities for artifact management for data science in the cloud.
Author: Saad Khan
Author-email: skhan8@mail.einstein.yu.edu
Requires-Python: >=3.6,<4.0
Classifier: Programming Language :: Python :: 3
Classifier: Programming Language :: Python :: 3.6
Classifier: Programming Language :: Python :: 3.7
Classifier: Programming Language :: Python :: 3.8
Provides-Extra: fireworks-ml
Requires-Dist: aiofiles (>=0.5.0,<0.6.0)
Requires-Dist: gcloud-aio-storage (>=5.4.0,<6.0.0)
Requires-Dist: google-cloud-storage (>=1.25,<2.0)
Requires-Dist: tqdm (>=4.41.1,<5.0.0)
Requires-Dist: uvloop (>=0.14.0,<0.15.0)
